{
  "city": "بندر گناوه",
  "city_en": "بندر گناوه",
  "lat": 29.5791,
  "lon": 50.517,
  "id": "134217",
  "data": {
    "latitude": 29.625,
    "longitude": 50.5,
    "generationtime_ms": 2.804398536682129,
    "utc_offset_seconds": 12600,
    "timezone": "Asia/Tehran",
    "timezone_abbreviation": "GMT+3:30",
    "elevation": 7.0,
    "current_weather_units": {
      "time": "iso8601",
      "interval": "seconds",
      "temperature": "°C",
      "windspeed": "km/h",
      "winddirection": "°",
      "is_day": "",
      "weathercode": "wmo code"
    },
    "current_weather": {
      "time": "2026-06-01T15:15",
      "interval": 900,
      "temperature": 41.2,
      "windspeed": 22.8,
      "winddirection": 288,
      "is_day": 1,
      "weathercode": 0
    },
    "hourly_units": {
      "time": "iso8601",
      "temperature_2m": "°C",
      "precipitation_probability": "%",
      "weather_code": "wmo code",
      "wind_speed_10m": "km/h"
    },
    "hourly": {
      "time": [
        "2026-06-01T00:00",
        "2026-06-01T01:00",
        "2026-06-01T02:00",
        "2026-06-01T03:00",
        "2026-06-01T04:00",
        "2026-06-01T05:00",
        "2026-06-01T06:00",
        "2026-06-01T07:00",
        "2026-06-01T08:00",
        "2026-06-01T09:00",
        "2026-06-01T10:00",
        "2026-06-01T11:00",
        "2026-06-01T12:00",
        "2026-06-01T13:00",
        "2026-06-01T14:00",
        "2026-06-01T15:00",
        "2026-06-01T16:00",
        "2026-06-01T17:00",
        "2026-06-01T18:00",
        "2026-06-01T19:00",
        "2026-06-01T20:00",
        "2026-06-01T21:00",
        "2026-06-01T22:00",
        "2026-06-01T23:00",
        "2026-06-02T00:00",
        "2026-06-02T01:00",
        "2026-06-02T02:00",
        "2026-06-02T03:00",
        "2026-06-02T04:00",
        "2026-06-02T05:00",
        "2026-06-02T06:00",
        "2026-06-02T07:00",
        "2026-06-02T08:00",
        "2026-06-02T09:00",
        "2026-06-02T10:00",
        "2026-06-02T11:00",
        "2026-06-02T12:00",
        "2026-06-02T13:00",
        "2026-06-02T14:00",
        "2026-06-02T15:00",
        "2026-06-02T16:00",
        "2026-06-02T17:00",
        "2026-06-02T18:00",
        "2026-06-02T19:00",
        "2026-06-02T20:00",
        "2026-06-02T21:00",
        "2026-06-02T22:00",
        "2026-06-02T23:00"
      ],
      "temperature_2m": [
        33.0,
        32.2,
        31.6,
        31.1,
        30.6,
        29.7,
        30.0,
        31.6,
        33.9,
        37.0,
        39.7,
        39.5,
        40.2,
        41.4,
        41.6,
        41.0,
        40.1,
        38.1,
        36.1,
        34.8,
        34.5,
        35.2,
        35.7,
        35.0,
        33.8,
        33.3,
        32.1,
        31.1,
        30.0,
        29.1,
        29.1,
        31.5,
        35.1,
        38.2,
        39.0,
        39.9,
        40.7,
        41.4,
        41.2,
        39.5,
        37.6,
        36.1,
        34.3,
        33.2,
        32.8,
        32.3,
        32.0,
        31.7
      ],
      "precipitation_probability": [
        0,
        0,
        0,
        0,
        0,
        0,
        0,
        0,
        0,
        0,
        0,
        0,
        0,
        0,
        0,
        0,
        0,
        0,
        0,
        0,
        0,
        0,
        0,
        0,
        0,
        0,
        0,
        0,
        0,
        0,
        0,
        0,
        0,
        0,
        0,
        0,
        0,
        0,
        0,
        0,
        0,
        0,
        0,
        0,
        0,
        0,
        0,
        0
      ],
      "weather_code": [
        0,
        0,
        0,
        0,
        0,
        0,
        0,
        0,
        0,
        0,
        0,
        0,
        0,
        0,
        0,
        0,
        0,
        0,
        0,
        0,
        0,
        0,
        0,
        0,
        0,
        0,
        0,
        0,
        0,
        0,
        0,
        0,
        0,
        0,
        0,
        0,
        0,
        0,
        0,
        0,
        0,
        0,
        0,
        0,
        0,
        0,
        0,
        0
      ],
      "wind_speed_10m": [
        18.3,
        18.0,
        20.5,
        18.2,
        13.6,
        9.7,
        10.5,
        13.0,
        13.2,
        9.9,
        11.0,
        16.1,
        19.1,
        21.3,
        22.5,
        22.4,
        20.3,
        16.6,
        14.6,
        12.6,
        11.9,
        13.2,
        14.3,
        11.8,
        10.4,
        8.1,
        6.0,
        5.2,
        5.1,
        5.1,
        4.0,
        3.7,
        4.6,
        9.0,
        14.7,
        18.2,
        21.2,
        22.8,
        22.8,
        21.8,
        18.4,
        16.6,
        15.5,
        13.1,
        10.8,
        9.7,
        8.2,
        7.7
      ]
    },
    "daily_units": {
      "time": "iso8601",
      "temperature_2m_max": "°C",
      "temperature_2m_min": "°C",
      "precipitation_probability_max": "%",
      "weather_code": "wmo code"
    },
    "daily": {
      "time": [
        "2026-06-01",
        "2026-06-02"
      ],
      "temperature_2m_max": [
        41.6,
        41.4
      ],
      "temperature_2m_min": [
        29.7,
        29.1
      ],
      "precipitation_probability_max": [
        0,
        0
      ],
      "weather_code": [
        0,
        0
      ]
    }
  }
}