{
  "city": "بندر انزلی",
  "city_en": "Bandar-e Anzali",
  "lat": 37.4727,
  "lon": 49.4587,
  "id": 149,
  "data": {
    "latitude": 37.4375,
    "longitude": 49.4375,
    "generationtime_ms": 0.8336305618286133,
    "utc_offset_seconds": 12600,
    "timezone": "Asia/Tehran",
    "timezone_abbreviation": "GMT+3:30",
    "elevation": -18.0,
    "current_weather_units": {
      "time": "iso8601",
      "interval": "seconds",
      "temperature": "°C",
      "windspeed": "km/h",
      "winddirection": "°",
      "is_day": "",
      "weathercode": "wmo code"
    },
    "current_weather": {
      "time": "2026-05-05T19:00",
      "interval": 900,
      "temperature": 15.8,
      "windspeed": 6.1,
      "winddirection": 87,
      "is_day": 1,
      "weathercode": 3
    },
    "daily_units": {
      "time": "iso8601",
      "temperature_2m_max": "°C",
      "temperature_2m_min": "°C",
      "precipitation_probability_max": "%"
    },
    "daily": {
      "time": [
        "2026-05-05",
        "2026-05-06",
        "2026-05-07",
        "2026-05-08",
        "2026-05-09",
        "2026-05-10",
        "2026-05-11"
      ],
      "temperature_2m_max": [
        17.9,
        16.3,
        20.1,
        20.8,
        21.3,
        17.9,
        17.5
      ],
      "temperature_2m_min": [
        15.3,
        15.2,
        14.7,
        13.9,
        12.4,
        11.9,
        16.3
      ],
      "precipitation_probability_max": [
        63,
        58,
        0,
        0,
        3,
        0,
        4
      ]
    }
  }
}